graph_visualization/__init__.py
graph_visualization/create_flask_app.py
graph_visualization/plot_graph.py
graph_visualization/tf_proto_to_json.py
graph_visualization/static/d3_graph.js
graph_visualization/templates/d3_graph.html
lightelligence_model_visualization-1.0.4.dist-info/METADATA
lightelligence_model_visualization-1.0.4.dist-info/WHEEL
lightelligence_model_visualization-1.0.4.dist-info/entry_points.txt
lightelligence_model_visualization-1.0.4.dist-info/top_level.txt
lightelligence_model_visualization-1.0.4.dist-info/RECORD
