Metadata-Version: 2.1
Name: lightelligence-model-visualization
Version: 1.0.4
Summary: An easy and interactive graph visualization tool for ML models!!!
Home-page: UNKNOWN
Author: Lightelligence
License: BSD
Platform: UNKNOWN
Requires-Python: >=3.6
Requires-Dist: Flask (==1.1.2)
Requires-Dist: networkx (==2.5)
Requires-Dist: tensorflow (==1.15.3)
